masterai_pptx2md/__init__.py
masterai_pptx2md/__version__.py
masterai_pptx2md/exceptions.py
masterai_pptx2md/http_file_types.py
masterai_pptx2md/models.py
masterai_pptx2md/outputter.py
masterai_pptx2md/parser.py
masterai_pptx2md/utils.py
masterai_pptx2md-25.8.6.dist-info/METADATA
masterai_pptx2md-25.8.6.dist-info/WHEEL
masterai_pptx2md-25.8.6.dist-info/top_level.txt
masterai_pptx2md-25.8.6.dist-info/RECORD
