Metadata-Version: 2.1
Name: masterai-pptx2md
Version: 25.8.6
Summary: masterai covert pptx to md
Home-page: 
Author: zhazhazhui
Author-email: zhazhahui@masterai.com
License: MIT
Classifier: License :: OSI Approved :: MIT License
Classifier: Programming Language :: Python :: 3.6
Classifier: Programming Language :: Python :: 3.7
Classifier: Programming Language :: Python :: 3.8
Classifier: Programming Language :: Python :: Implementation :: CPython
Classifier: Programming Language :: Python :: Implementation :: PyPy
Requires-Python: >=3.6.0
Requires-Dist: pydantic
Requires-Dist: tqdm >=4
Requires-Dist: python-pptx
Requires-Dist: oss2
Requires-Dist: pillow >=10.0.1
Requires-Dist: pillow-avif-plugin ==1.4.6
Requires-Dist: pillow-heif ==0.21.0
